to_ico/__init__.py
to_ico/to_ico.py
to_ico-1.1.data/scripts/to_ico.py
to_ico-1.1.dist-info/LICENSE
to_ico-1.1.dist-info/METADATA
to_ico-1.1.dist-info/WHEEL
to_ico-1.1.dist-info/entry_points.txt
to_ico-1.1.dist-info/top_level.txt
to_ico-1.1.dist-info/RECORD
