Metadata-Version: 2.1
Name: to-ico
Version: 1.1
Summary: A small png to ico convertor script. Just type 'to-ico' in console.
Home-page: https://github.com/amshinski/to-ico
Author: amshinski
Author-email: amshinski@gmail.com
License: UNKNOWN
Keywords: ico,console,convert,image
Platform: UNKNOWN
Classifier: Programming Language :: Python :: 3.8
Classifier: License :: OSI Approved :: MIT License
Classifier: Operating System :: OS Independent
Requires-Python: >=3.6
Requires-Dist: Pillow
